{
	"mixins": "stonehearth:mixins:placed_object",
	"components": {
		"model_variants": {
			"default": {
				"models": [
					"file(water_garden_clay.qb)",
					{
						"type": "one_of",
						"items": [
							"file(water_garden_clay_pink.qb)",
							"file(water_garden_clay_purple.qb)",
							"file(water_garden_clay_white.qb)",
							"file(water_garden_clay_yellow.qb)"
						]
					}
				]
			}
		},
		"mob": {
			"model_origin": { "x": 0.5, "y": 0, "z": 0.5 },
			"region_origin": { "x": 0.5, "y": 0, "z": 0.5 }
		}
	},
	"entity_data": {
		"stonehearth:catalog": {
			"display_name": "i18n(swamp_goblins:entities.decoration.water_garden_clay.display_name)",
			"description": "i18n(swamp_goblins:entities.decoration.water_garden.description)",
			"icon": "file(water_garden_clay.png)",
			"category": "decoration",
			"material_tags": ["firefly_made", "clay", "decoration", "stockpile_decoration"]
		}
	}
}